datasploit/__init__.py
datasploit/active_default_file_check.py
datasploit/active_scan.py
datasploit/config_sample.py
datasploit/datasploit.py
datasploit/datasploit_config.py
datasploit/domainOsint.py
datasploit/emailOsint.py
datasploit/ipOsint.py
datasploit/osint_runner.py
datasploit/usernameOsint.py
datasploit/domain/__init__.py
datasploit/domain/base.py
datasploit/domain/domain_GooglePDF.py
datasploit/domain/domain_censys.py
datasploit/domain/domain_checkpunkspider.py
datasploit/domain/domain_dnsrecords.py
datasploit/domain/domain_emailhunter.py
datasploit/domain/domain_forumsearch.py
datasploit/domain/domain_github.py
datasploit/domain/domain_history.py
datasploit/domain/domain_pagelinks.py
datasploit/domain/domain_pastes.py
datasploit/domain/domain_shodan.py
datasploit/domain/domain_subdomains.py
datasploit/domain/domain_wappalyzer.py
datasploit/domain/domain_whois.py
datasploit/domain/domain_wikileaks.py
datasploit/domain/domain_zoomeye.py
datasploit/domain/template.py
datasploit/emails/__init__.py
datasploit/emails/base.py
datasploit/emails/email_basic_checks.py
datasploit/emails/email_clearbit.py
datasploit/emails/email_fullcontact.py
datasploit/emails/email_haveibeenpwned.py
datasploit/emails/email_pastes.py
datasploit/emails/email_scribd.py
datasploit/emails/email_slideshare.py
datasploit/emails/email_whoismind.py
datasploit/emails/template.py
datasploit/ip/__init__.py
datasploit/ip/base.py
datasploit/ip/ip_shodan.py
datasploit/ip/ip_virustotal.py
datasploit/ip/ip_whois.py
datasploit/ip/template.py
datasploit/username/__init__.py
datasploit/username/base.py
datasploit/username/template.py
datasploit/username/username_gitscrape.py
datasploit/username/username_gituserdetails.py
datasploit/username/username_keybase.py
datasploit/username/username_profilepic.py
datasploit/username/username_twitterdetails.py
datasploit/username/username_usernamesearch.py
datasploit-1.0.dist-info/DESCRIPTION.rst
datasploit-1.0.dist-info/METADATA
datasploit-1.0.dist-info/RECORD
datasploit-1.0.dist-info/WHEEL
datasploit-1.0.dist-info/entry_points.txt
datasploit-1.0.dist-info/metadata.json
datasploit-1.0.dist-info/top_level.txt
