Metadata-Version: 2.0
Name: datasploit
Version: 1.0
Summary: A framework to perform various OSINT techniques, aggregate all the raw data, and give data in multiple formats.
Home-page: https://github.com/DataSploit/datasploit
Author: Shubham Mittal, Sudhanshu Chauhan, Kunal Aggarwal
Author-email: upgoingstaar@gmail.com
License: GPLv3
Platform: UNKNOWN
Requires-Dist: BeautifulSoup (==3.2.1)
Requires-Dist: anyjson (==0.3.3)
Requires-Dist: beautifulsoup4 (==4.4.1)
Requires-Dist: billiard (==3.3.0.23)
Requires-Dist: bs4 (==0.0.1)
Requires-Dist: clearbit (==0.1.4)
Requires-Dist: config (==0.3.9)
Requires-Dist: dnspython (==1.14.0)
Requires-Dist: future (==0.15.2)
Requires-Dist: idna (==2.1)
Requires-Dist: ipwhois (==0.15.1)
Requires-Dist: json2html (==1.0.1)
Requires-Dist: lxml (==3.6.0)
Requires-Dist: piplapis-python (==5.1.0)
Requires-Dist: pymongo (==3.3.0)
Requires-Dist: python-Wappalyzer (==0.2.2)
Requires-Dist: python-whois (==0.6.2)
Requires-Dist: pytz (==2016.6.1)
Requires-Dist: requests (==2.10.0)
Requires-Dist: requests-file (==1.4)
Requires-Dist: simplejson (==3.8.2)
Requires-Dist: termcolor
Requires-Dist: tldextract (==2.0.1)
Requires-Dist: tqdm (==4.7.6)
Requires-Dist: tweepy (==3.5.0)
